src/__init__.py
src/calculate_filtering_metrics.py
src/classifier.py
src/compare.py
src/decode_msceleb_dataset.py
src/download_and_extract.py
src/facenet.py
src/freeze_graph.py
src/lfw.py
src/train_softmax.py
src/train_tripletloss.py
src/validate_on_lfw.py
src/align/__init__.py
src/align/align_dataset_mtcnn.py
src/align/detect_face.py
src/generative/__init__.py
src/generative/calculate_attribute_vectors.py
src/generative/calculate_dataset_normalization.py
src/generative/modify_attribute.py
src/generative/train_vae.py
src/generative/models/__init__.py
src/generative/models/dfc_vae.py
src/generative/models/dfc_vae_large.py
src/generative/models/dfc_vae_resnet.py
src/generative/models/vae_base.py
src/models/__init__.py
src/models/dummy.py
src/models/inception_resnet_v1.py
src/models/inception_resnet_v2.py
src/models/squeezenet.py
vfacenet-1.0.0.dist-info/DESCRIPTION.rst
vfacenet-1.0.0.dist-info/METADATA
vfacenet-1.0.0.dist-info/RECORD
vfacenet-1.0.0.dist-info/WHEEL
vfacenet-1.0.0.dist-info/metadata.json
vfacenet-1.0.0.dist-info/top_level.txt
